{"t": "Title VEH Vehicles", "p": "/us/nsn/lco/council/code/VEH", "et": "container", "dj": "/us/nsn/lco/council/code/index.json", "fh": "/us/nsn/lco/council/code/VEH/index.full.html", "sc": "Title VEH", "sp": "library|Lac Courte Oreilles Tribal Code of Law|VEH", "c": [{"t": "Chapter VEH.3 Vehicle Licensing and Registration Code of the Lac Courte Oreilles Band of Lake Superior Chippewa Indians", "p": "/us/nsn/lco/council/code/VEH.3", "et": "container", "sc": "Chapter VEH.3", "sp": "library|Lac Courte Oreilles Tribal Code of Law|VEH|VEH.3", "c": [{"t": "Subchapter VEH.3.1 Motor Vehicle Registration Ordinance", "p": "/us/nsn/lco/council/code/VEH.3.1", "et": "container", "sc": "Subchapter VEH.3.1", "sp": "library|Lac Courte Oreilles Tribal Code of Law|VEH|VEH.3|VEH.3.1", "c": [{"t": "VEH.3.1.010 Title", "p": "/us/nsn/lco/council/code/VEH.3.1.010", "et": "section", "sc": "Section VEH.3.1.010", "sp": "library|Lac Courte Oreilles Tribal Code of Law|VEH|VEH.3|VEH.3.1|VEH.3.1.010"}, {"t": "VEH.3.1.020 Authority", "p": "/us/nsn/lco/council/code/VEH.3.1.020", "et": "section", "sc": "Section VEH.3.1.020", "sp": "library|Lac Courte Oreilles Tribal Code of Law|VEH|VEH.3|VEH.3.1|VEH.3.1.020"}, {"t": "VEH.3.1.030 Purpose and Policy", "p": "/us/nsn/lco/council/code/VEH.3.1.030", "et": "section", "sc": "Section VEH.3.1.030", "sp": "library|Lac Courte Oreilles Tribal Code of Law|VEH|VEH.3|VEH.3.1|VEH.3.1.030"}, {"t": "VEH.3.1.040 Jurisdiction", "p": "/us/nsn/lco/council/code/VEH.3.1.040", "et": "section", "sc": "Section VEH.3.1.040", "sp": "library|Lac Courte Oreilles Tribal Code of Law|VEH|VEH.3|VEH.3.1|VEH.3.1.040"}, {"t": "VEH.3.1.050 Construction", "p": "/us/nsn/lco/council/code/VEH.3.1.050", "et": "section", "sc": "Section VEH.3.1.050", "sp": "library|Lac Courte Oreilles Tribal Code of Law|VEH|VEH.3|VEH.3.1|VEH.3.1.050"}, {"t": "VEH.3.1.060 Severability", "p": "/us/nsn/lco/council/code/VEH.3.1.060", "et": "section", "sc": "Section VEH.3.1.060", "sp": "library|Lac Courte Oreilles Tribal Code of Law|VEH|VEH.3|VEH.3.1|VEH.3.1.060"}, {"t": "VEH.3.1.070 Repealer", "p": "/us/nsn/lco/council/code/VEH.3.1.070", "et": "section", "sc": "Section VEH.3.1.070", "sp": "library|Lac Courte Oreilles Tribal Code of Law|VEH|VEH.3|VEH.3.1|VEH.3.1.070"}, {"t": "VEH.3.1.080 Definitions", "p": "/us/nsn/lco/council/code/VEH.3.1.080", "et": "section", "sc": "Section VEH.3.1.080", "sp": "library|Lac Courte Oreilles Tribal Code of Law|VEH|VEH.3|VEH.3.1|VEH.3.1.080", "c": [{"t": "(a)", "p": "/us/nsn/lco/council/code/VEH.3.1.080#(a)", "et": "para", "sc": "Section VEH.3.1.080(a)", "c": [{"t": "(1)", "p": "/us/nsn/lco/council/code/VEH.3.1.080#(a)(1)", "et": "para", "sc": "Section VEH.3.1.080(a)(1)", "x": "A motor vehicle designed and used primarily for carrying persons but which "}, {"t": "(2)", "p": "/us/nsn/lco/council/code/VEH.3.1.080#(a)(2)", "et": "para", "sc": "Section VEH.3.1.080(a)(2)", "x": "A motor vehicle capable of speeds in excess of 30 miles per hour on a dry, "}], "x": "\"Automobile\" means any of the following:"}, {"t": "(b)", "p": "/us/nsn/lco/council/code/VEH.3.1.080#(b)", "et": "para", "sc": "Section VEH.3.1.080(b)", "x": "\"Department\" means the Licensing Department, or any other department of the"}, {"t": "(c)", "p": "/us/nsn/lco/council/code/VEH.3.1.080#(c)", "et": "para", "sc": "Section VEH.3.1.080(c)", "x": "\"Gross weight\" means the weight of the vehicle equipped for service plus th"}, {"t": "(d)", "p": "/us/nsn/lco/council/code/VEH.3.1.080#(d)", "et": "para", "sc": "Section VEH.3.1.080(d)", "x": "\"Highway\" means all public ways and thoroughfares and bridges on the same. "}, {"t": "(e)", "p": "/us/nsn/lco/council/code/VEH.3.1.080#(e)", "et": "para", "sc": "Section VEH.3.1.080(e)", "x": "\"Identification number\" means the numbers, letters or combination of number"}, {"t": "(f)", "p": "/us/nsn/lco/council/code/VEH.3.1.080#(f)", "et": "para", "sc": "Section VEH.3.1.080(f)", "x": "\"Junked\" means dismantled for parts or scrapped."}, {"t": "(g)", "p": "/us/nsn/lco/council/code/VEH.3.1.080#(g)", "et": "para", "sc": "Section VEH.3.1.080(g)", "x": "\"Lac Courte Oreilles\" means Lac Courte Oreilles Band of Lake Superior Chipp"}, {"t": "(h)", "p": "/us/nsn/lco/council/code/VEH.3.1.080#(h)", "et": "para", "sc": "Section VEH.3.1.080(h)", "x": "\"Lac Courte Oreilles Tribal member\" means a member of the Lac Courte Oreill"}, {"t": "(i)", "p": "/us/nsn/lco/council/code/VEH.3.1.080#(i)", "et": "para", "sc": "Section VEH.3.1.080(i)", "c": [{"t": "(1)", "p": "/us/nsn/lco/council/code/VEH.3.1.080#(i)(1)", "et": "para", "sc": "Section VEH.3.1.080(i)(1)", "x": "A bicycle-type vehicle with fully operative pedals for propulsion by human "}, {"t": "(2)", "p": "/us/nsn/lco/council/code/VEH.3.1.080#(i)(2)", "et": "para", "sc": "Section VEH.3.1.080(i)(2)", "x": "A Type 1 motorcycle with an automatic transmission and an engine certified "}], "x": "\"Moped\" means any of the following motor vehicles capable of speeds of not "}, {"t": "(j)", "p": "/us/nsn/lco/council/code/VEH.3.1.080#(j)", "et": "para", "sc": "Section VEH.3.1.080(j)", "c": [{"t": "(1)", "p": "/us/nsn/lco/council/code/VEH.3.1.080#(j)(1)", "et": "para", "sc": "Section VEH.3.1.080(j)(1)", "c": [{"t": "(A)", "p": "/us/nsn/lco/council/code/VEH.3.1.080#(j)(1)(A)", "et": "para", "sc": "Section VEH.3.1.080(j)(1)(A)", "x": "Is designed and built with two (2) wheels in tandem and a seat for the oper"}, {"t": "(B)", "p": "/us/nsn/lco/council/code/VEH.3.1.080#(j)(1)(B)", "et": "para", "sc": "Section VEH.3.1.080(j)(1)(B)", "x": "Is designed and built to have no more than three (3) wheels, seating for th"}], "x": "Type 1 is a motor vehicle which meets either of the following conditions:"}, {"t": "(2)", "p": "/us/nsn/lco/council/code/VEH.3.1.080#(j)(2)", "et": "para", "sc": "Section VEH.3.1.080(j)(2)", "x": "Type 2 is a motor vehicle designed and built to have at least three (3) whe"}], "x": "\"Motorcycle\" means a motor vehicle, excluding a tractor or an all-terrain v"}, {"t": "(k)", "p": "/us/nsn/lco/council/code/VEH.3.1.080#(k)", "et": "para", "sc": "Section VEH.3.1.080(k)", "x": "\"Motor home\" means motor vehicle designed to be operated upon a highway for"}, {"t": "(l)", "p": "/us/nsn/lco/council/code/VEH.3.1.080#(l)", "et": "para", "sc": "Section VEH.3.1.080(l)", "x": "\"Nonresident\" means a person not a resident of the Reservation."}, {"t": "(m)", "p": "/us/nsn/lco/council/code/VEH.3.1.080#(m)", "et": "para", "sc": "Section VEH.3.1.080(m)", "x": "\"Other jurisdiction\" or \"another jurisdiction\" means territory other than t"}, {"t": "(n)", "p": "/us/nsn/lco/council/code/VEH.3.1.080#(n)", "et": "para", "sc": "Section VEH.3.1.080(n)", "x": "\"Owner\" means a person who holds the legal title of a vehicle, except that "}, {"t": "(o)", "p": "/us/nsn/lco/council/code/VEH.3.1.080#(o)", "et": "para", "sc": "Section VEH.3.1.080(o)", "x": "\"Personal identifier\" means a name, street address, post office box number "}, {"t": "(p)", "p": "/us/nsn/lco/council/code/VEH.3.1.080#(p)", "et": "para", "sc": "Section VEH.3.1.080(p)", "c": [{"t": "(1)", "p": "/us/nsn/lco/council/code/VEH.3.1.080#(p)(1)", "et": "para", "sc": "Section VEH.3.1.080(p)(1)", "x": "Cannot walk 200 feet or more without stopping to rest."}, {"t": "(2)", "p": "/us/nsn/lco/council/code/VEH.3.1.080#(p)(2)", "et": "para", "sc": "Section VEH.3.1.080(p)(2)", "x": "Cannot walk without the use of, or assistance from, another person or"}, {"t": "(3)", "p": "/us/nsn/lco/council/code/VEH.3.1.080#(p)(3)", "et": "para", "sc": "Section VEH.3.1.080(p)(3)", "x": "Is restricted by lung disease."}, {"t": "(4)", "p": "/us/nsn/lco/council/code/VEH.3.1.080#(p)(4)", "et": "para", "sc": "Section VEH.3.1.080(p)(4)", "x": "Uses portable oxygen."}, {"t": "(5)", "p": "/us/nsn/lco/council/code/VEH.3.1.080#(p)(5)", "et": "para", "sc": "Section VEH.3.1.080(p)(5)", "x": "Has cardiac condition to the extent that functional limitations are present"}, {"t": "(6)", "p": "/us/nsn/lco/council/code/VEH.3.1.080#(p)(6)", "et": "para", "sc": "Section VEH.3.1.080(p)(6)", "x": "Is severely limited in the ability to walk due to an arthritic neurological"}, {"t": "(7)", "p": "/us/nsn/lco/council/code/VEH.3.1.080#(p)(7)", "et": "para", "sc": "Section VEH.3.1.080(p)(7)", "x": "Has a degree of disability equal to that specified in pars. (1) to (6)."}], "x": "\"Person with a disability that limits or impairs the ability to walk\" means"}, {"t": "(q)", "p": "/us/nsn/lco/council/code/VEH.3.1.080#(q)", "et": "para", "sc": "Section VEH.3.1.080(q)", "x": "\"Reservation\" means the Reservation of the Lac Courte Oreilles Band of Lake"}, {"t": "(r)", "p": "/us/nsn/lco/council/code/VEH.3.1.080#(r)", "et": "para", "sc": "Section VEH.3.1.080(r)", "x": "\"Special interest vehicle\" means a motor vehicle of any age which has not b"}, {"t": "(s)", "p": "/us/nsn/lco/council/code/VEH.3.1.080#(s)", "et": "para", "sc": "Section VEH.3.1.080(s)", "x": "\"Truck\" means every motor vehicle 10,000 pounds or under designed, used or "}, {"t": "(t)", "p": "/us/nsn/lco/council/code/VEH.3.1.080#(t)", "et": "para", "sc": "Section VEH.3.1.080(t)", "x": "\"Vehicle\" means every device in, upon or which any person or property is or"}]}]}, {"t": "Subchapter VEH.3.2 Registration Periods", "p": "/us/nsn/lco/council/code/VEH.3.2", "et": "container", "sc": "Subchapter VEH.3.2", "sp": "library|Lac Courte Oreilles Tribal Code of Law|VEH|VEH.3|VEH.3.2", "c": [{"t": "VEH.3.2.010 Regular Automobiles", "p": "/us/nsn/lco/council/code/VEH.3.2.010", "et": "section", "sc": "Section VEH.3.2.010", "sp": "library|Lac Courte Oreilles Tribal Code of Law|VEH|VEH.3|VEH.3.2|VEH.3.2.010", "c": [{"t": "(a)", "p": "/us/nsn/lco/council/code/VEH.3.2.010#(a)", "et": "para", "sc": "Section VEH.3.2.010(a)", "x": "All automobiles customarily owned by Lac Courte Oreilles tribal members sha"}, {"t": "(b)", "p": "/us/nsn/lco/council/code/VEH.3.2.010#(b)", "et": "para", "sc": "Section VEH.3.2.010(b)", "x": "The annual fee for each automobile registered in this jurisdiction and unde"}]}, {"t": "VEH.3.2.020 Registration Periods for Private Automobiles", "p": "/us/nsn/lco/council/code/VEH.3.2.020", "et": "section", "sc": "Section VEH.3.2.020", "sp": "library|Lac Courte Oreilles Tribal Code of Law|VEH|VEH.3|VEH.3.2|VEH.3.2.020", "c": [{"t": "(a)", "p": "/us/nsn/lco/council/code/VEH.3.2.020#(a)", "et": "para", "sc": "Section VEH.3.2.020(a)", "x": "All automobiles shall be registered by the department according to a monthl"}, {"t": "(b)", "p": "/us/nsn/lco/council/code/VEH.3.2.020#(b)", "et": "para", "sc": "Section VEH.3.2.020(b)", "x": "There are established 12 registration periods, each to be designated by a c"}, {"t": "(c)", "p": "/us/nsn/lco/council/code/VEH.3.2.020#(c)", "et": "para", "sc": "Section VEH.3.2.020(c)", "c": [{"t": "(1)", "p": "/us/nsn/lco/council/code/VEH.3.2.020#(c)(1)", "et": "para", "sc": "Section VEH.3.2.020(c)(1)", "x": "If the applicant holds current registration plates which were removed from "}, {"t": "(2)", "p": "/us/nsn/lco/council/code/VEH.3.2.020#(c)(2)", "et": "para", "sc": "Section VEH.3.2.020(c)(2)", "x": "If the applicant does not hold current registration plates under the circum"}], "x": "All automobiles subject to registration under monthly series systems shall "}, {"t": "(d)", "p": "/us/nsn/lco/council/code/VEH.3.2.020#(d)", "et": "para", "sc": "Section VEH.3.2.020(d)", "x": "All registration fees, applicable fines, penalties, forfeitures and assessm"}, {"t": "(e)", "p": "/us/nsn/lco/council/code/VEH.3.2.020#(e)", "et": "para", "sc": "Section VEH.3.2.020(e)", "x": "The department shall be responsible for the administration of this ordinanc"}, {"t": "(f)", "p": "/us/nsn/lco/council/code/VEH.3.2.020#(f)", "et": "para", "sc": "Section VEH.3.2.020(f)", "x": "All applications and registrations shall be retained by the department for "}]}, {"t": "VEH.3.2.030 Special Registration Period for Vehicles Other than Private Automobiles", "p": "/us/nsn/lco/council/code/VEH.3.2.030", "et": "section", "sc": "Section VEH.3.2.030", "sp": "library|Lac Courte Oreilles Tribal Code of Law|VEH|VEH.3|VEH.3.2|VEH.3.2.030", "c": [{"t": "(a)", "p": "/us/nsn/lco/council/code/VEH.3.2.030#(a)", "et": "para", "sc": "Section VEH.3.2.030(a)", "x": "The department shall require that any vehicle other than private automobile"}, {"t": "(b)", "p": "/us/nsn/lco/council/code/VEH.3.2.030#(b)", "et": "para", "sc": "Section VEH.3.2.030(b)", "x": "There are established 12 registration periods, each to be designed by a cal"}, {"t": "(c)", "p": "/us/nsn/lco/council/code/VEH.3.2.030#(c)", "et": "para", "sc": "Section VEH.3.2.030(c)", "c": [{"t": "(1)", "p": "/us/nsn/lco/council/code/VEH.3.2.030#(c)(1)", "et": "para", "sc": "Section VEH.3.2.030(c)(1)", "x": "If the applicant holds registration plates which were removed from a vehicl"}, {"t": "(2)", "p": "/us/nsn/lco/council/code/VEH.3.2.030#(c)(2)", "et": "para", "sc": "Section VEH.3.2.030(c)(2)", "x": "If the applicant does not hold current registration plates under the circum"}], "x": "All vehicles subject to registration under the monthly series system under "}, {"t": "(d)", "p": "/us/nsn/lco/council/code/VEH.3.2.030#(d)", "et": "para", "sc": "Section VEH.3.2.030(d)", "x": "Section VEH.3.11.010 applies to any vehicles registered according to the mo"}]}, {"t": "VEH.3.2.040 Biennial Registration", "p": "/us/nsn/lco/council/code/VEH.3.2.040", "et": "section", "sc": "Section VEH.3.2.040", "sp": "library|Lac Courte Oreilles Tribal Code of Law|VEH|VEH.3|VEH.3.2|VEH.3.2.040", "c": [{"t": "(a)", "p": "/us/nsn/lco/council/code/VEH.3.2.040#(a)", "et": "para", "sc": "Section VEH.3.2.040(a)", "x": "A motorcycle or moped, as specified in Section VEH.3.7.040. The registratio"}]}, {"t": "VEH.3.2.050 Vehicles Exempt from Registration", "p": "/us/nsn/lco/council/code/VEH.3.2.050", "et": "section", "sc": "Section VEH.3.2.050", "sp": "library|Lac Courte Oreilles Tribal Code of Law|VEH|VEH.3|VEH.3.2|VEH.3.2.050", "c": [{"t": "(a)", "p": "/us/nsn/lco/council/code/VEH.3.2.050#(a)", "et": "para", "sc": "Section VEH.3.2.050(a)", "x": "Operated in accordance with the provisions exempting nonresident or foreign"}, {"t": "(b)", "p": "/us/nsn/lco/council/code/VEH.3.2.050#(b)", "et": "para", "sc": "Section VEH.3.2.050(b)", "x": "A farm tractor used exclusively in agricultural operations, including thres"}, {"t": "(c)", "p": "/us/nsn/lco/council/code/VEH.3.2.050#(c)", "et": "para", "sc": "Section VEH.3.2.050(c)", "x": "A trailer or semi-trailer used exclusively for the transportation of farm m"}, {"t": "(d)", "p": "/us/nsn/lco/council/code/VEH.3.2.050#(d)", "et": "para", "sc": "Section VEH.3.2.050(d)", "x": "A fork-lift truck, a specially constructed road or truck tractor used for s"}, {"t": "(e)", "p": "/us/nsn/lco/council/code/VEH.3.2.050#(e)", "et": "para", "sc": "Section VEH.3.2.050(e)", "x": "A trailer or camping trailer having a gross weight of 3,000 pounds or less "}, {"t": "(f)", "p": "/us/nsn/lco/council/code/VEH.3.2.050#(f)", "et": "para", "sc": "Section VEH.3.2.050(f)", "x": "A trailer not operated in conjunction with a motor vehicle; or"}, {"t": "(g)", "p": "/us/nsn/lco/council/code/VEH.3.2.050#(g)", "et": "para", "sc": "Section VEH.3.2.050(g)", "x": "A new motor vehicle being operated only across a highway from point of manu"}, {"t": "(h)", "p": "/us/nsn/lco/council/code/VEH.3.2.050#(h)", "et": "para", "sc": "Section VEH.3.2.050(h)", "x": "A piece of road machinery."}]}]}, {"t": "Subchapter VEH.3.3 Application for Registration", "p": "/us/nsn/lco/council/code/VEH.3.3", "et": "container", "sc": "Subchapter VEH.3.3", "sp": "library|Lac Courte Oreilles Tribal Code of Law|VEH|VEH.3|VEH.3.3", "c": [{"t": "VEH.3.3.010 Applications in General", "p": "/us/nsn/lco/council/code/VEH.3.3.010", "et": "section", "sc": "Section VEH.3.3.010", "sp": "library|Lac Courte Oreilles Tribal Code of Law|VEH|VEH.3|VEH.3.3|VEH.3.3.010", "c": [{"t": "(a)", "p": "/us/nsn/lco/council/code/VEH.3.3.010#(a)", "et": "para", "sc": "Section VEH.3.3.010(a)", "x": "Application for original registration and for renewal of registration shall"}, {"t": "(b)", "p": "/us/nsn/lco/council/code/VEH.3.3.010#(b)", "et": "para", "sc": "Section VEH.3.3.010(b)", "x": "The forms for application for original registration and for renewal of regi"}]}, {"t": "VEH.3.3.020 Original Applications", "p": "/us/nsn/lco/council/code/VEH.3.3.020", "et": "section", "sc": "Section VEH.3.3.020", "sp": "library|Lac Courte Oreilles Tribal Code of Law|VEH|VEH.3|VEH.3.3|VEH.3.3.020", "c": [{"t": "(a)", "p": "/us/nsn/lco/council/code/VEH.3.3.020#(a)", "et": "para", "sc": "Section VEH.3.3.020(a)", "c": [{"t": "(1)", "p": "/us/nsn/lco/council/code/VEH.3.3.020#(a)(1)", "et": "para", "sc": "Section VEH.3.3.020(a)(1)", "x": "The name of the owner."}, {"t": "(2)", "p": "/us/nsn/lco/council/code/VEH.3.3.020#(a)(2)", "et": "para", "sc": "Section VEH.3.3.020(a)(2)", "x": "A description of the vehicle, including make, model, identification number "}, {"t": "(3)", "p": "/us/nsn/lco/council/code/VEH.3.3.020#(a)(3)", "et": "para", "sc": "Section VEH.3.3.020(a)(3)", "x": "Such further information as the department may reasonably require to enable"}], "x": "Applications for original registration of a vehicle shall contain the follo"}, {"t": "(b)", "p": "/us/nsn/lco/council/code/VEH.3.3.020#(b)", "et": "para", "sc": "Section VEH.3.3.020(b)", "x": "The department may accept an application and complete registration of a veh"}]}, {"t": "VEH.3.3.030 Applicants Under 18", "p": "/us/nsn/lco/council/code/VEH.3.3.030", "et": "section", "sc": "Section VEH.3.3.030", "sp": "library|Lac Courte Oreilles Tribal Code of Law|VEH|VEH.3|VEH.3.3|VEH.3.3.030"}, {"t": "VEH.3.3.040 Renewal Applications", "p": "/us/nsn/lco/council/code/VEH.3.3.040", "et": "section", "sc": "Section VEH.3.3.040", "sp": "library|Lac Courte Oreilles Tribal Code of Law|VEH|VEH.3|VEH.3.3|VEH.3.3.040", "c": [{"t": "(a)", "p": "/us/nsn/lco/council/code/VEH.3.3.040#(a)", "et": "para", "sc": "Section VEH.3.3.040(a)", "x": "Applications for renewal of registration shall contain the information requ"}, {"t": "(b)", "p": "/us/nsn/lco/council/code/VEH.3.3.040#(b)", "et": "para", "sc": "Section VEH.3.3.040(b)", "c": [{"t": "(1)", "p": "/us/nsn/lco/council/code/VEH.3.3.040#(b)(1)", "et": "para", "sc": "Section VEH.3.3.040(b)(1)", "x": "The application form or an accompanying document shall include a list of an"}, {"t": "(2)", "p": "/us/nsn/lco/council/code/VEH.3.3.040#(b)(2)", "et": "para", "sc": "Section VEH.3.3.040(b)(2)", "x": "If there is a citation for any nonmoving traffic violation entered against "}], "x": "At least 30 days prior to the expiration of a vehicle's registration, the d"}]}, {"t": "VEH.3.3.050 Grounds for Refusing Registration", "p": "/us/nsn/lco/council/code/VEH.3.3.050", "et": "section", "sc": "Section VEH.3.3.050", "sp": "library|Lac Courte Oreilles Tribal Code of Law|VEH|VEH.3|VEH.3.3|VEH.3.3.050", "c": [{"t": "(a)", "p": "/us/nsn/lco/council/code/VEH.3.3.050#(a)", "et": "para", "sc": "Section VEH.3.3.050(a)", "x": "The vehicle owner applying for registration is not a Lac Courte Oreilles me"}, {"t": "(b)", "p": "/us/nsn/lco/council/code/VEH.3.3.050#(b)", "et": "para", "sc": "Section VEH.3.3.050(b)", "x": "The required vehicle registration fee imposed by the department for a vehic"}, {"t": "(c)", "p": "/us/nsn/lco/council/code/VEH.3.3.050#(c)", "et": "para", "sc": "Section VEH.3.3.050(c)", "c": [{"t": "(1)", "p": "/us/nsn/lco/council/code/VEH.3.3.050#(c)(1)", "et": "para", "sc": "Section VEH.3.3.050(c)(1)", "x": "Unless exempted by rule of the document, the mileage disclosure from the mo"}, {"t": "(2)", "p": "/us/nsn/lco/council/code/VEH.3.3.050#(c)(2)", "et": "para", "sc": "Section VEH.3.3.050(c)(2)", "x": "Other information or documents required by law or by the department pursuan"}, {"t": "(3)", "p": "/us/nsn/lco/council/code/VEH.3.3.050#(c)(3)", "et": "para", "sc": "Section VEH.3.3.050(c)(3)", "x": "Proof of Lac Courte Oreilles membership by enrollment card or number."}], "x": "The applicant has failed to furnish any of the following:"}, {"t": "(d)", "p": "/us/nsn/lco/council/code/VEH.3.3.050#(d)", "et": "para", "sc": "Section VEH.3.3.050(d)", "x": "Where the applicant does not hold a valid certificate of title and is not e"}, {"t": "(e)", "p": "/us/nsn/lco/council/code/VEH.3.3.050#(e)", "et": "para", "sc": "Section VEH.3.3.050(e)", "x": "The applicant's registration has been suspended or revoked and such suspens"}, {"t": "(f)", "p": "/us/nsn/lco/council/code/VEH.3.3.050#(f)", "et": "para", "sc": "Section VEH.3.3.050(f)", "x": "The vehicle is exempt from registration and voluntary registration of the v"}]}]}, {"t": "Subchapter VEH.3.4 Registration Plates", "p": "/us/nsn/lco/council/code/VEH.3.4", "et": "container", "sc": "Subchapter VEH.3.4", "sp": "library|Lac Courte Oreilles Tribal Code of Law|VEH|VEH.3|VEH.3.4", "c": [{"t": "VEH.3.4.010 Design, Procurement and Issuance of Registration Plates", "p": "/us/nsn/lco/council/code/VEH.3.4.010", "et": "section", "sc": "Section VEH.3.4.010", "sp": "library|Lac Courte Oreilles Tribal Code of Law|VEH|VEH.3|VEH.3.4|VEH.3.4.010", "c": [{"t": "(a)", "p": "/us/nsn/lco/council/code/VEH.3.4.010#(a)", "et": "para", "sc": "Section VEH.3.4.010(a)", "x": "The department upon registering a vehicle pursuant to Section VEH.3.2.010 a"}, {"t": "(b)", "p": "/us/nsn/lco/council/code/VEH.3.4.010#(b)", "et": "para", "sc": "Section VEH.3.4.010(b)", "c": [{"t": "(1)", "p": "/us/nsn/lco/council/code/VEH.3.4.010#(b)(1)", "et": "para", "sc": "Section VEH.3.4.010(b)(1)", "x": "The registration number assigned to the vehicle or owner. The registration "}, {"t": "(2)", "p": "/us/nsn/lco/council/code/VEH.3.4.010#(b)(2)", "et": "para", "sc": "Section VEH.3.4.010(b)(2)", "x": "The name \"Lac Courte Oreilles\""}, {"t": "(3)", "p": "/us/nsn/lco/council/code/VEH.3.4.010#(b)(3)", "et": "para", "sc": "Section VEH.3.4.010(b)(3)", "x": "An indication of the period for which the specific plate is issued or the d"}], "x": "All registration plates shall have displayed upon them the following:"}, {"t": "(c)", "p": "/us/nsn/lco/council/code/VEH.3.4.010#(c)", "et": "para", "sc": "Section VEH.3.4.010(c)", "x": "In lieu of issuing a new plate upon each renewal of registration of a vehic"}]}, {"t": "VEH.3.4.020 Application for and Issuance of Special Plates", "p": "/us/nsn/lco/council/code/VEH.3.4.020", "et": "section", "sc": "Section VEH.3.4.020", "sp": "library|Lac Courte Oreilles Tribal Code of Law|VEH|VEH.3|VEH.3.4|VEH.3.4.020", "c": [{"t": "(a)", "p": "/us/nsn/lco/council/code/VEH.3.4.020#(a)", "et": "para", "sc": "Section VEH.3.4.020(a)", "x": "Disabled Lac Courte Oreilles Residents."}, {"t": "(b)", "p": "/us/nsn/lco/council/code/VEH.3.4.020#(b)", "et": "para", "sc": "Section VEH.3.4.020(b)", "x": "Disabled Lac Courte Oreilles Veterans."}, {"t": "(c)", "p": "/us/nsn/lco/council/code/VEH.3.4.020#(c)", "et": "para", "sc": "Section VEH.3.4.020(c)", "x": "Lac Courte Oreilles Veteran/Congressional Medal of Honor."}, {"t": "(d)", "p": "/us/nsn/lco/council/code/VEH.3.4.020#(d)", "et": "para", "sc": "Section VEH.3.4.020(d)", "c": [{"t": "(1)", "p": "/us/nsn/lco/council/code/VEH.3.4.020#(d)(1)", "et": "para", "sc": "Section VEH.3.4.020(d)(1)", "x": "Upon application to register an automobile or truck by any Lac Courte Oreil"}, {"t": "(2)", "p": "/us/nsn/lco/council/code/VEH.3.4.020#(d)(2)", "et": "para", "sc": "Section VEH.3.4.020(d)(2)", "x": "A person who maintains no more than one registration under this subsection "}, {"t": "(3)", "p": "/us/nsn/lco/council/code/VEH.3.4.020#(d)(3)", "et": "para", "sc": "Section VEH.3.4.020(d)(3)", "x": "For each additional vehicle, a person who maintains more than one registrat"}, {"t": "(4)", "p": "/us/nsn/lco/council/code/VEH.3.4.020#(d)(4)", "et": "para", "sc": "Section VEH.3.4.020(d)(4)", "x": "If a registration plate has been issued to a person under par (1), upon app"}, {"t": "(5)", "p": "/us/nsn/lco/council/code/VEH.3.4.020#(d)(5)", "et": "para", "sc": "Section VEH.3.4.020(d)(5)", "x": "The department shall charge a fee of $15.00 for re-issuance of any plate un"}], "x": "Prisoner of War."}, {"t": "(e)", "p": "/us/nsn/lco/council/code/VEH.3.4.020#(e)", "et": "para", "sc": "Section VEH.3.4.020(e)", "c": [{"t": "(1)", "p": "/us/nsn/lco/council/code/VEH.3.4.020#(e)(1)", "et": "para", "sc": "Section VEH.3.4.020(e)(1)", "x": "World War II veterans, Korean War veterans, Vietnam War veterans, Persian G"}, {"t": "(2)", "p": "/us/nsn/lco/council/code/VEH.3.4.020#(e)(2)", "et": "para", "sc": "Section VEH.3.4.020(e)(2)", "x": "The annual registration fee shall be $40.00. There shall be an additional f"}, {"t": "(3)", "p": "/us/nsn/lco/council/code/VEH.3.4.020#(e)(3)", "et": "para", "sc": "Section VEH.3.4.020(e)(3)", "c": [{"t": "(A)", "p": "/us/nsn/lco/council/code/VEH.3.4.020#(e)(3)(A)", "et": "para", "sc": "Section VEH.3.4.020(e)(3)(A)", "x": "Dispose of the special plates in a manner prescribed by the department;"}, {"t": "(B)", "p": "/us/nsn/lco/council/code/VEH.3.4.020#(e)(3)(B)", "et": "para", "sc": "Section VEH.3.4.020(e)(3)(B)", "x": "In addition to the regular application fee, pay a $4 fee for the issuance o"}, {"t": "(C)", "p": "/us/nsn/lco/council/code/VEH.3.4.020#(e)(3)(C)", "et": "para", "sc": "Section VEH.3.4.020(e)(3)(C)", "x": "Return the certificate of title to the department for correction."}], "x": "If an individual in possession of special plates or of personalized plates "}], "x": "Veterans Plates."}]}, {"t": "VEH.3.4.030 Personalized License Plates", "p": "/us/nsn/lco/council/code/VEH.3.4.030", "et": "section", "sc": "Section VEH.3.4.030", "sp": "library|Lac Courte Oreilles Tribal Code of Law|VEH|VEH.3|VEH.3.4|VEH.3.4.030", "c": [{"t": "(a)", "p": "/us/nsn/lco/council/code/VEH.3.4.030#(a)", "et": "para", "sc": "Section VEH.3.4.030(a)", "x": "A registration plate for a motor vehicle registered under this ordinance wh"}, {"t": "(b)", "p": "/us/nsn/lco/council/code/VEH.3.4.030#(b)", "et": "para", "sc": "Section VEH.3.4.030(b)", "x": "A registration plate of the same color and design as provided in Section VE"}, {"t": "(c)", "p": "/us/nsn/lco/council/code/VEH.3.4.030#(c)", "et": "para", "sc": "Section VEH.3.4.030(c)", "c": [{"t": "(1)", "p": "/us/nsn/lco/council/code/VEH.3.4.030#(c)(1)", "et": "para", "sc": "Section VEH.3.4.030(c)(1)", "x": "The request and alternate thereto is received by the department in writing "}], "x": "The department shall issue personalized registration plates only upon reque"}, {"t": "(d)", "p": "/us/nsn/lco/council/code/VEH.3.4.030#(d)", "et": "para", "sc": "Section VEH.3.4.030(d)", "c": [{"t": "(1)", "p": "/us/nsn/lco/council/code/VEH.3.4.030#(d)(1)", "et": "para", "sc": "Section VEH.3.4.030(d)(1)", "x": "The requested combination of numbers or letters has not already been issued"}], "x": "The request is accompanied by the proper fee, an application for original o"}, {"t": "(e)", "p": "/us/nsn/lco/council/code/VEH.3.4.030#(e)", "et": "para", "sc": "Section VEH.3.4.030(e)", "x": "In addition to the regular application fee provided for in this ordinance, "}, {"t": "(f)", "p": "/us/nsn/lco/council/code/VEH.3.4.030#(f)", "et": "para", "sc": "Section VEH.3.4.030(f)", "x": "Each personalized registration plate issued shall be reserved for the recip"}, {"t": "(g)", "p": "/us/nsn/lco/council/code/VEH.3.4.030#(g)", "et": "para", "sc": "Section VEH.3.4.030(g)", "c": [{"t": "(1)", "p": "/us/nsn/lco/council/code/VEH.3.4.030#(g)(1)", "et": "para", "sc": "Section VEH.3.4.030(g)(1)", "x": "Dispose of the personalized plate in a manner prescribed by the department;"}, {"t": "(2)", "p": "/us/nsn/lco/council/code/VEH.3.4.030#(g)(2)", "et": "para", "sc": "Section VEH.3.4.030(g)(2)", "x": "In addition to the regular application fee, pay a $4 fee for the issuance o"}, {"t": "(3)", "p": "/us/nsn/lco/council/code/VEH.3.4.030#(g)(3)", "et": "para", "sc": "Section VEH.3.4.030(g)(3)", "x": "Return the certificate of title to the department for correction."}], "x": "If an individual in possession of a personalized registration plate does no"}, {"t": "(h)", "p": "/us/nsn/lco/council/code/VEH.3.4.030#(h)", "et": "para", "sc": "Section VEH.3.4.030(h)", "x": "The department may refuse to issue any combination of letters or numbers, o"}, {"t": "(i)", "p": "/us/nsn/lco/council/code/VEH.3.4.030#(i)", "et": "para", "sc": "Section VEH.3.4.030(i)", "x": "The department may cancel and order the return of any personalized registra"}]}]}, {"t": "Subchapter VEH.3.5 Display of Registration Plates", "p": "/us/nsn/lco/council/code/VEH.3.5", "et": "container", "sc": "Subchapter VEH.3.5", "sp": "library|Lac Courte Oreilles Tribal Code of Law|VEH|VEH.3|VEH.3.5", "c": [{"t": "VEH.3.5.010 Placement of Plates or Decals on Vehicles", "p": "/us/nsn/lco/council/code/VEH.3.5.010", "et": "section", "sc": "Section VEH.3.5.010", "sp": "library|Lac Courte Oreilles Tribal Code of Law|VEH|VEH.3|VEH.3.5|VEH.3.5.010", "c": [{"t": "(a)", "p": "/us/nsn/lco/council/code/VEH.3.5.010#(a)", "et": "para", "sc": "Section VEH.3.5.010(a)", "x": "Whenever two (2) registration plates are licensed for a vehicle, one (1) pl"}, {"t": "(b)", "p": "/us/nsn/lco/council/code/VEH.3.5.010#(b)", "et": "para", "sc": "Section VEH.3.5.010(b)", "x": "Any registration decal or tag issued by the department shall be placed on t"}, {"t": "(c)", "p": "/us/nsn/lco/council/code/VEH.3.5.010#(c)", "et": "para", "sc": "Section VEH.3.5.010(c)", "x": "Registration plates shall be attached firmly and rigidly in a horizontal po"}, {"t": "(d)", "p": "/us/nsn/lco/council/code/VEH.3.5.010#(d)", "et": "para", "sc": "Section VEH.3.5.010(d)", "c": [{"t": "(1)", "p": "/us/nsn/lco/council/code/VEH.3.5.010#(d)(1)", "et": "para", "sc": "Section VEH.3.5.010(d)(1)", "x": "A person who operates a vehicle for which a current registration plate or i"}, {"t": "(2)", "p": "/us/nsn/lco/council/code/VEH.3.5.010#(d)(2)", "et": "para", "sc": "Section VEH.3.5.010(d)(2)", "x": "A person who operates a vehicle with a registration plate attached in a non"}, {"t": "(3)", "p": "/us/nsn/lco/council/code/VEH.3.5.010#(d)(3)", "et": "para", "sc": "Section VEH.3.5.010(d)(3)", "x": "A person who operates a vehicle with the registration plate in an illegible"}], "x": "Any of the following may be required to forfeit not more than $200:"}]}]}, {"t": "Subchapter VEH.3.6 Issuance of Replacement Plates", "p": "/us/nsn/lco/council/code/VEH.3.6", "et": "container", "sc": "Subchapter VEH.3.6", "sp": "library|Lac Courte Oreilles Tribal Code of Law|VEH|VEH.3|VEH.3.6", "c": [{"t": "VEH.3.6.010 Lost or Destroyed Plates", "p": "/us/nsn/lco/council/code/VEH.3.6.010", "et": "section", "sc": "Section VEH.3.6.010", "sp": "library|Lac Courte Oreilles Tribal Code of Law|VEH|VEH.3|VEH.3.6|VEH.3.6.010", "c": [{"t": "(a)", "p": "/us/nsn/lco/council/code/VEH.3.6.010#(a)", "et": "para", "sc": "Section VEH.3.6.010(a)", "x": "Whenever a current registration plate is lost or destroyed, the owner of th"}, {"t": "(b)", "p": "/us/nsn/lco/council/code/VEH.3.6.010#(b)", "et": "para", "sc": "Section VEH.3.6.010(b)", "x": "Upon satisfactory proof of the loss or destruction of a specialized plate o"}]}, {"t": "VEH.3.6.020 Illegible Plates", "p": "/us/nsn/lco/council/code/VEH.3.6.020", "et": "section", "sc": "Section VEH.3.6.020", "sp": "library|Lac Courte Oreilles Tribal Code of Law|VEH|VEH.3|VEH.3.6|VEH.3.6.020"}, {"t": "VEH.3.6.030 Replacement Plates", "p": "/us/nsn/lco/council/code/VEH.3.6.030", "et": "section", "sc": "Section VEH.3.6.030", "sp": "library|Lac Courte Oreilles Tribal Code of Law|VEH|VEH.3|VEH.3.6|VEH.3.6.030"}]}, {"t": "Subchapter VEH.3.7 Department to Compile Registration Lists", "p": "/us/nsn/lco/council/code/VEH.3.7", "et": "container", "sc": "Subchapter VEH.3.7", "sp": "library|Lac Courte Oreilles Tribal Code of Law|VEH|VEH.3|VEH.3.7", "c": [{"t": "VEH.3.7.010 Maintaining Lists", "p": "/us/nsn/lco/council/code/VEH.3.7.010", "et": "section", "sc": "Section VEH.3.7.010", "sp": "library|Lac Courte Oreilles Tribal Code of Law|VEH|VEH.3|VEH.3.7|VEH.3.7.010", "c": [{"t": "(a)", "p": "/us/nsn/lco/council/code/VEH.3.7.010#(a)", "et": "para", "sc": "Section VEH.3.7.010(a)", "x": "At intervals selected by the department, the department shall compile a lis"}, {"t": "(b)", "p": "/us/nsn/lco/council/code/VEH.3.7.010#(b)", "et": "para", "sc": "Section VEH.3.7.010(b)", "x": "The department shall compile a list of new automobile and motor truck regis"}]}, {"t": "VEH.3.7.020 Access to Lists", "p": "/us/nsn/lco/council/code/VEH.3.7.020", "et": "section", "sc": "Section VEH.3.7.020", "sp": "library|Lac Courte Oreilles Tribal Code of Law|VEH|VEH.3|VEH.3.7|VEH.3.7.020", "c": [{"t": "(a)", "p": "/us/nsn/lco/council/code/VEH.3.7.020#(a)", "et": "para", "sc": "Section VEH.3.7.020(a)", "c": [{"t": "(1)", "p": "/us/nsn/lco/council/code/VEH.3.7.020#(a)(1)", "et": "para", "sc": "Section VEH.3.7.020(a)(1)", "x": "To the Lac Courte Oreilles Law Enforcement Department, one copy of each aut"}, {"t": "(2)", "p": "/us/nsn/lco/council/code/VEH.3.7.020#(a)(2)", "et": "para", "sc": "Section VEH.3.7.020(a)(2)", "x": "To any other public officer or agency that provides in writing reasonable r"}], "x": "Upon request, the department shall distribute free of charge registration l"}, {"t": "(b)", "p": "/us/nsn/lco/council/code/VEH.3.7.020#(b)", "et": "para", "sc": "Section VEH.3.7.020(b)", "x": "Except as provided in Section VEH.3.7.030 public officers and agencies rece"}]}, {"t": "VEH.3.7.030 Limitations on Disclosure", "p": "/us/nsn/lco/council/code/VEH.3.7.030", "et": "section", "sc": "Section VEH.3.7.030", "sp": "library|Lac Courte Oreilles Tribal Code of Law|VEH|VEH.3|VEH.3.7|VEH.3.7.030", "c": [{"t": "(a)", "p": "/us/nsn/lco/council/code/VEH.3.7.030#(a)", "et": "para", "sc": "Section VEH.3.7.030(a)", "x": "In providing copies under this section of any written information collected"}, {"t": "(b)", "p": "/us/nsn/lco/council/code/VEH.3.7.030#(b)", "et": "para", "sc": "Section VEH.3.7.030(b)", "c": [{"t": "(1)", "p": "/us/nsn/lco/council/code/VEH.3.7.030#(b)(1)", "et": "para", "sc": "Section VEH.3.7.030(b)(1)", "x": "A person receiving a registration list under Section VEH.3.7.020(a) and Sec"}, {"t": "(2)", "p": "/us/nsn/lco/council/code/VEH.3.7.030#(b)(2)", "et": "para", "sc": "Section VEH.3.7.030(b)(2)", "x": "A law enforcement agency"}, {"t": "(3)", "p": "/us/nsn/lco/council/code/VEH.3.7.030#(b)(3)", "et": "para", "sc": "Section VEH.3.7.030(b)(3)", "x": "An insurer authorized to write property and casualty insurance in the State"}, {"t": "(4)", "p": "/us/nsn/lco/council/code/VEH.3.7.030#(b)(4)", "et": "para", "sc": "Section VEH.3.7.030(b)(4)", "x": "A person obtaining registration or title information for use in the conduct"}], "x": "Paragraph (a) does not apply to any of the following:"}, {"t": "(c)", "p": "/us/nsn/lco/council/code/VEH.3.7.030#(c)", "et": "para", "sc": "Section VEH.3.7.030(c)", "c": [{"t": "(1)", "p": "/us/nsn/lco/council/code/VEH.3.7.030#(c)(1)", "et": "para", "sc": "Section VEH.3.7.030(c)(1)", "x": "Any person who willfully discloses a personal identifier in violation of th"}, {"t": "(2)", "p": "/us/nsn/lco/council/code/VEH.3.7.030#(c)(2)", "et": "para", "sc": "Section VEH.3.7.030(c)(2)", "x": "Any person who willfully requests or obtains a personal identifier from the"}], "x": "Any person who has received under par. (b) a personal identifier of any per"}]}, {"t": "VEH.3.7.040 Biennial Motorcycle Fees", "p": "/us/nsn/lco/council/code/VEH.3.7.040", "et": "section", "sc": "Section VEH.3.7.040", "sp": "library|Lac Courte Oreilles Tribal Code of Law|VEH|VEH.3|VEH.3.7|VEH.3.7.040", "c": [{"t": "(a)", "p": "/us/nsn/lco/council/code/VEH.3.7.040#(a)", "et": "para", "sc": "Section VEH.3.7.040(a)", "c": [{"t": "(1)", "p": "/us/nsn/lco/council/code/VEH.3.7.040#(a)(1)", "et": "para", "sc": "Section VEH.3.7.040(a)(1)", "x": "Registration plates under this section expire on April 30 of even numbered "}, {"t": "(2)", "p": "/us/nsn/lco/council/code/VEH.3.7.040#(a)(2)", "et": "para", "sc": "Section VEH.3.7.040(a)(2)", "x": "One license plate is sent by the department of each cycle registered."}], "x": "For each motorcycle or moped with a curb weight of 1,499 pounds or less, wh"}]}, {"t": "VEH.3.7.050 Calculation of Registration Fees Relating to Gross Weight: Trucks", "p": "/us/nsn/lco/council/code/VEH.3.7.050", "et": "section", "sc": "Section VEH.3.7.050", "sp": "library|Lac Courte Oreilles Tribal Code of Law|VEH|VEH.3|VEH.3.7|VEH.3.7.050", "c": [{"t": "(a)", "p": "/us/nsn/lco/council/code/VEH.3.7.050#(a)", "et": "para", "sc": "Section VEH.3.7.050(a)", "x": "Unless otherwise noted, for each truck under this section, a yearly registr"}, {"t": "(b)", "p": "/us/nsn/lco/council/code/VEH.3.7.050#(b)", "et": "para", "sc": "Section VEH.3.7.050(b)", "x": "The following schedule shall be used in determining fees based on gross wei"}]}, {"t": "VEH.3.7.060 Motor Homes", "p": "/us/nsn/lco/council/code/VEH.3.7.060", "et": "section", "sc": "Section VEH.3.7.060", "sp": "library|Lac Courte Oreilles Tribal Code of Law|VEH|VEH.3|VEH.3.7|VEH.3.7.060", "c": [{"t": "(a)", "p": "/us/nsn/lco/council/code/VEH.3.7.060#(a)", "et": "para", "sc": "Section VEH.3.7.060(a)", "x": "Unless otherwise noted, for each mobile home under this section, a yearly r"}, {"t": "(b)", "p": "/us/nsn/lco/council/code/VEH.3.7.060#(b)", "et": "para", "sc": "Section VEH.3.7.060(b)", "x": "The following schedule shall be used in determining fees based on gross wei"}, {"t": "(c)", "p": "/us/nsn/lco/council/code/VEH.3.7.060#(c)", "et": "para", "sc": "Section VEH.3.7.060(c)", "x": "Upon payment of the fee prescribed by law, a vehicle subject to registratio"}]}]}, {"t": "Subchapter VEH.3.8 Special Registration Fees for Certain Vehicles", "p": "/us/nsn/lco/council/code/VEH.3.8", "et": "container", "sc": "Subchapter VEH.3.8", "sp": "library|Lac Courte Oreilles Tribal Code of Law|VEH|VEH.3|VEH.3.8", "c": [{"t": "VEH.3.8.010 Lac Courte Oreilles Government Vehicles", "p": "/us/nsn/lco/council/code/VEH.3.8.010", "et": "section", "sc": "Section VEH.3.8.010", "sp": "library|Lac Courte Oreilles Tribal Code of Law|VEH|VEH.3|VEH.3.8|VEH.3.8.010", "c": [{"t": "(a)", "p": "/us/nsn/lco/council/code/VEH.3.8.010#(a)", "et": "para", "sc": "Section VEH.3.8.010(a)", "x": "A fee of $5 shall be paid to the department for the original issuance of a "}, {"t": "(b)", "p": "/us/nsn/lco/council/code/VEH.3.8.010#(b)", "et": "para", "sc": "Section VEH.3.8.010(b)", "x": "A fee of $5 shall be paid to the department for the original issuance of a "}]}]}, {"t": "Subchapter VEH.3.9 Antique Motor Vehicles; Registration, Plates, Use", "p": "/us/nsn/lco/council/code/VEH.3.9", "et": "container", "sc": "Subchapter VEH.3.9", "sp": "library|Lac Courte Oreilles Tribal Code of Law|VEH|VEH.3|VEH.3.9", "c": [{"t": "VEH.3.9.010 Antique Motor Vehicles", "p": "/us/nsn/lco/council/code/VEH.3.9.010", "et": "section", "sc": "Section VEH.3.9.010", "sp": "library|Lac Courte Oreilles Tribal Code of Law|VEH|VEH.3|VEH.3.9|VEH.3.9.010", "c": [{"t": "(a)", "p": "/us/nsn/lco/council/code/VEH.3.9.010#(a)", "et": "para", "sc": "Section VEH.3.9.010(a)", "x": "Any person who is a resident of the Reservation and the owner or subsequent"}, {"t": "(b)", "p": "/us/nsn/lco/council/code/VEH.3.9.010#(b)", "et": "para", "sc": "Section VEH.3.9.010(b)", "x": "Any person who registers an antique motor vehicle under par. (a) may furnis"}, {"t": "(c)", "p": "/us/nsn/lco/council/code/VEH.3.9.010#(c)", "et": "para", "sc": "Section VEH.3.9.010(c)", "x": "Unless inconsistent with this section, the provisions applicable to other m"}]}]}, {"t": "Subchapter VEH.3.10 Special Interest Vehicles: Registration, Plates, Use", "p": "/us/nsn/lco/council/code/VEH.3.10", "et": "container", "sc": "Subchapter VEH.3.10", "sp": "library|Lac Courte Oreilles Tribal Code of Law|VEH|VEH.3|VEH.3.10", "c": [{"t": "VEH.3.10.010 Special Interest Vehicle/Collectors Special Vehicle", "p": "/us/nsn/lco/council/code/VEH.3.10.010", "et": "section", "sc": "Section VEH.3.10.010", "sp": "library|Lac Courte Oreilles Tribal Code of Law|VEH|VEH.3|VEH.3.10|VEH.3.10.010", "c": [{"t": "(a)", "p": "/us/nsn/lco/council/code/VEH.3.10.010#(a)", "et": "para", "sc": "Section VEH.3.10.010(a)", "x": "Any person who is the owner of a special interest vehicle which is 20 or mo"}, {"t": "(b)", "p": "/us/nsn/lco/council/code/VEH.3.10.010#(b)", "et": "para", "sc": "Section VEH.3.10.010(b)", "x": "The fee to register a collector vehicle under par. (a) is a one time fee of"}, {"t": "(c)", "p": "/us/nsn/lco/council/code/VEH.3.10.010#(c)", "et": "para", "sc": "Section VEH.3.10.010(c)", "x": "Collector special plates are available to LCO tribal members with a valid c"}, {"t": "(d)", "p": "/us/nsn/lco/council/code/VEH.3.10.010#(d)", "et": "para", "sc": "Section VEH.3.10.010(d)", "x": "The department shall furnish the owner of the vehicle with registrations pl"}, {"t": "(e)", "p": "/us/nsn/lco/council/code/VEH.3.10.010#(e)", "et": "para", "sc": "Section VEH.3.10.010(e)", "x": "Each collector applying for special interest vehicle registration plates wi"}, {"t": "(f)", "p": "/us/nsn/lco/council/code/VEH.3.10.010#(f)", "et": "para", "sc": "Section VEH.3.10.010(f)", "c": [{"t": "(1)", "p": "/us/nsn/lco/council/code/VEH.3.10.010#(f)(1)", "et": "para", "sc": "Section VEH.3.10.010(f)(1)", "x": "Motor vehicles may not transport passengers for hire."}, {"t": "(2)", "p": "/us/nsn/lco/council/code/VEH.3.10.010#(f)(2)", "et": "para", "sc": "Section VEH.3.10.010(f)(2)", "x": "Trucks may not haul material weighing more than 500 pounds."}, {"t": "(3)", "p": "/us/nsn/lco/council/code/VEH.3.10.010#(f)(3)", "et": "para", "sc": "Section VEH.3.10.010(f)(3)", "x": "No special interest vehicle may be operated upon any highway within the Res"}], "x": "The vehicle may be used as are other vehicles of the same type except:"}, {"t": "(g)", "p": "/us/nsn/lco/council/code/VEH.3.10.010#(g)", "et": "para", "sc": "Section VEH.3.10.010(g)", "x": "Unless inconsistent with this section, the provisions applicable to other v"}]}]}, {"t": "Subchapter VEH.3.11 Part-Year Fees for Private Automobiles", "p": "/us/nsn/lco/council/code/VEH.3.11", "et": "container", "sc": "Subchapter VEH.3.11", "sp": "library|Lac Courte Oreilles Tribal Code of Law|VEH|VEH.3|VEH.3.11", "c": [{"t": "VEH.3.11.010 Calculation of Partial Fees", "p": "/us/nsn/lco/council/code/VEH.3.11.010", "et": "section", "sc": "Section VEH.3.11.010", "sp": "library|Lac Courte Oreilles Tribal Code of Law|VEH|VEH.3|VEH.3.11|VEH.3.11.010", "c": [{"t": "(a)", "p": "/us/nsn/lco/council/code/VEH.3.11.010#(a)", "et": "para", "sc": "Section VEH.3.11.010(a)", "x": "The applicant for registration of an automobile under the monthly series sy"}, {"t": "(b)", "p": "/us/nsn/lco/council/code/VEH.3.11.010#(b)", "et": "para", "sc": "Section VEH.3.11.010(b)", "c": [{"t": "(1)", "p": "/us/nsn/lco/council/code/VEH.3.11.010#(b)(1)", "et": "para", "sc": "Section VEH.3.11.010(b)(1)", "x": "If the annual fee prescribed for the automobile being registered is higher "}], "x": "If the applicant for registration holds current registration plates which w"}, {"t": "(c)", "p": "/us/nsn/lco/council/code/VEH.3.11.010#(c)", "et": "para", "sc": "Section VEH.3.11.010(c)", "c": [{"t": "(1)", "p": "/us/nsn/lco/council/code/VEH.3.11.010#(c)(1)", "et": "para", "sc": "Section VEH.3.11.010(c)(1)", "x": "If the first operation of an automobile under circumstances making the owne"}, {"t": "(2)", "p": "/us/nsn/lco/council/code/VEH.3.11.010#(c)(2)", "et": "para", "sc": "Section VEH.3.11.010(c)(2)", "x": "In the case of an automobile which has not previously been registered or wh"}], "x": "For the purpose of computing the registration fee payable upon registration"}]}, {"t": "VEH.3.11.020 When Part-Period Fees Payable for Vehicles Other than Automobiles;", "p": "/us/nsn/lco/council/code/VEH.3.11.020", "et": "section", "sc": "Section VEH.3.11.020", "sp": "library|Lac Courte Oreilles Tribal Code of Law|VEH|VEH.3|VEH.3.11|VEH.3.11.020", "c": [{"t": "(a)", "p": "/us/nsn/lco/council/code/VEH.3.11.020#(a)", "et": "para", "sc": "Section VEH.3.11.020(a)", "x": "The vehicle has not previously been registered within this Reservation; or"}, {"t": "(b)", "p": "/us/nsn/lco/council/code/VEH.3.11.020#(b)", "et": "para", "sc": "Section VEH.3.11.020(b)", "c": [{"t": "(1)", "p": "/us/nsn/lco/council/code/VEH.3.11.020#(b)(1)", "et": "para", "sc": "Section VEH.3.11.020(b)(1)", "x": "The vehicle in the meantime has been registered in another jurisdiction and"}, {"t": "(2)", "p": "/us/nsn/lco/council/code/VEH.3.11.020#(b)(2)", "et": "para", "sc": "Section VEH.3.11.020(b)(2)", "x": "The vehicle was transferred to the applicant after the expiration of the la"}, {"t": "(3)", "p": "/us/nsn/lco/council/code/VEH.3.11.020#(b)(3)", "et": "para", "sc": "Section VEH.3.11.020(b)(3)", "x": "At least 12 months have elapsed since the end of the period for which the v"}, {"t": "(4)", "p": "/us/nsn/lco/council/code/VEH.3.11.020#(b)(4)", "et": "para", "sc": "Section VEH.3.11.020(b)(4)", "x": "The vehicle is a motorcycle which has been transferred to the applicant and"}, {"t": "(5)", "p": "/us/nsn/lco/council/code/VEH.3.11.020#(b)(5)", "et": "para", "sc": "Section VEH.3.11.020(b)(5)", "x": "The vehicle which has been transferred to the applicant is a motor home or "}, {"t": "(6)", "p": "/us/nsn/lco/council/code/VEH.3.11.020#(b)(6)", "et": "para", "sc": "Section VEH.3.11.020(b)(6)", "x": "The vehicle is subject to the provisions of sub. (5); or"}], "x": "The vehicle previously was registered within this Reservation; but"}, {"t": "(c)", "p": "/us/nsn/lco/council/code/VEH.3.11.020#(c)", "et": "para", "sc": "Section VEH.3.11.020(c)", "x": "The vehicle is a replacement for a registered vehicle which has been junked"}, {"t": "(d)", "p": "/us/nsn/lco/council/code/VEH.3.11.020#(d)", "et": "para", "sc": "Section VEH.3.11.020(d)", "x": "The vehicle is owned by a person who has been in active military service an"}, {"t": "(e)", "p": "/us/nsn/lco/council/code/VEH.3.11.020#(e)", "et": "para", "sc": "Section VEH.3.11.020(e)", "c": [{"t": "(1)", "p": "/us/nsn/lco/council/code/VEH.3.11.020#(e)(1)", "et": "para", "sc": "Section VEH.3.11.020(e)(1)", "x": "For vehicles registered under the conditions in Section VEH.3.11.020(a), Se"}, {"t": "(2)", "p": "/us/nsn/lco/council/code/VEH.3.11.020#(e)(2)", "et": "para", "sc": "Section VEH.3.11.020(e)(2)", "x": "For the registration of a replacement vehicle under the conditions set fort"}], "x": "Part-period registration fees shall be computed as follows:"}]}, {"t": "VEH.3.11.030 Transferred Plates or Plates No Longer in Use", "p": "/us/nsn/lco/council/code/VEH.3.11.030", "et": "section", "sc": "Section VEH.3.11.030", "sp": "library|Lac Courte Oreilles Tribal Code of Law|VEH|VEH.3|VEH.3.11|VEH.3.11.030", "c": [{"t": "(a)", "p": "/us/nsn/lco/council/code/VEH.3.11.030#(a)", "et": "para", "sc": "Section VEH.3.11.030(a)", "x": "The transferee of a vehicle registered as provided in Section VEH.3.2.030 i"}, {"t": "(b)", "p": "/us/nsn/lco/council/code/VEH.3.11.030#(b)", "et": "para", "sc": "Section VEH.3.11.030(b)", "x": "A person retaining a set of plates removed from a vehicle which was junked "}, {"t": "(c)", "p": "/us/nsn/lco/council/code/VEH.3.11.030#(c)", "et": "para", "sc": "Section VEH.3.11.030(c)", "x": "A person retaining a set of plates removed from a motorcycle may receive cr"}, {"t": "(d)", "p": "/us/nsn/lco/council/code/VEH.3.11.030#(d)", "et": "para", "sc": "Section VEH.3.11.030(d)", "x": "This section does not apply to vehicles registered at a fee of $5 under Sec"}, {"t": "(e)", "p": "/us/nsn/lco/council/code/VEH.3.11.030#(e)", "et": "para", "sc": "Section VEH.3.11.030(e)", "x": "The credit or plate transfer provisions authorized under this section do no"}]}, {"t": "VEH.3.11.040 Re-Registration Required for Vehicles Subject to a Different Fee", "p": "/us/nsn/lco/council/code/VEH.3.11.040", "et": "section", "sc": "Section VEH.3.11.040", "sp": "library|Lac Courte Oreilles Tribal Code of Law|VEH|VEH.3|VEH.3.11|VEH.3.11.040"}, {"t": "VEH.3.11.050 Refundable Fees", "p": "/us/nsn/lco/council/code/VEH.3.11.050", "et": "section", "sc": "Section VEH.3.11.050", "sp": "library|Lac Courte Oreilles Tribal Code of Law|VEH|VEH.3|VEH.3.11|VEH.3.11.050", "c": [{"t": "(a)", "p": "/us/nsn/lco/council/code/VEH.3.11.050#(a)", "et": "para", "sc": "Section VEH.3.11.050(a)", "x": "The department shall not refund a fee paid to it except when expressly auth"}, {"t": "(b)", "p": "/us/nsn/lco/council/code/VEH.3.11.050#(b)", "et": "para", "sc": "Section VEH.3.11.050(b)", "x": "Upon request, the department shall refund 50 percent of a registration fee "}]}, {"t": "VEH.3.11.060 Change of Address", "p": "/us/nsn/lco/council/code/VEH.3.11.060", "et": "section", "sc": "Section VEH.3.11.060", "sp": "library|Lac Courte Oreilles Tribal Code of Law|VEH|VEH.3|VEH.3.11|VEH.3.11.060", "c": [{"t": "(a)", "p": "/us/nsn/lco/council/code/VEH.3.11.060#(a)", "et": "para", "sc": "Section VEH.3.11.060(a)", "x": "Whenever any person, after applying for and receiving registration plates, "}, {"t": "(b)", "p": "/us/nsn/lco/council/code/VEH.3.11.060#(b)", "et": "para", "sc": "Section VEH.3.11.060(b)", "x": "Any person who fails to comply with any of the requirements of par. (a) may"}]}, {"t": "VEH.3.11.070 Reinstatement of Suspended or Revoked Registration", "p": "/us/nsn/lco/council/code/VEH.3.11.070", "et": "section", "sc": "Section VEH.3.11.070", "sp": "library|Lac Courte Oreilles Tribal Code of Law|VEH|VEH.3|VEH.3.11|VEH.3.11.070", "c": [{"t": "(a)", "p": "/us/nsn/lco/council/code/VEH.3.11.070#(a)", "et": "para", "sc": "Section VEH.3.11.070(a)", "x": "Except as provided in par. (b), the department shall charge a fee of $25 to"}, {"t": "(b)", "p": "/us/nsn/lco/council/code/VEH.3.11.070#(b)", "et": "para", "sc": "Section VEH.3.11.070(b)", "x": "Par. (a) does not apply to the reinstatement of a registration suspended or"}]}, {"t": "VEH.3.11.080 Exemption of Nonresidents and Foreign Registered Vehicles", "p": "/us/nsn/lco/council/code/VEH.3.11.080", "et": "section", "sc": "Section VEH.3.11.080", "sp": "library|Lac Courte Oreilles Tribal Code of Law|VEH|VEH.3|VEH.3.11|VEH.3.11.080", "c": [{"t": "(a)", "p": "/us/nsn/lco/council/code/VEH.3.11.080#(a)", "et": "para", "sc": "Section VEH.3.11.080(a)", "x": "The vehicle carries a registration plate indicating the registration in suc"}, {"t": "(b)", "p": "/us/nsn/lco/council/code/VEH.3.11.080#(b)", "et": "para", "sc": "Section VEH.3.11.080(b)", "x": "The vehicle is owned by a nonresident of the Reservation."}, {"t": "(c)", "p": "/us/nsn/lco/council/code/VEH.3.11.080#(c)", "et": "para", "sc": "Section VEH.3.11.080(c)", "x": "If the owner of such vehicle moves within the jurisdiction Lac Courte Oreil"}]}, {"t": "VEH.3.11.090 Reciprocal Agreements", "p": "/us/nsn/lco/council/code/VEH.3.11.090", "et": "section", "sc": "Section VEH.3.11.090", "sp": "library|Lac Courte Oreilles Tribal Code of Law|VEH|VEH.3|VEH.3.11|VEH.3.11.090"}]}, {"t": "Subchapter VEH.3.12 Penalties", "p": "/us/nsn/lco/council/code/VEH.3.12", "et": "container", "sc": "Subchapter VEH.3.12", "sp": "library|Lac Courte Oreilles Tribal Code of Law|VEH|VEH.3|VEH.3.12", "c": [{"t": "VEH.3.12.010 Fraudulent Applications", "p": "/us/nsn/lco/council/code/VEH.3.12.010", "et": "section", "sc": "Section VEH.3.12.010", "sp": "library|Lac Courte Oreilles Tribal Code of Law|VEH|VEH.3|VEH.3.12|VEH.3.12.010"}, {"t": "VEH.3.12.020 Improper Use of Evidence of Registration", "p": "/us/nsn/lco/council/code/VEH.3.12.020", "et": "section", "sc": "Section VEH.3.12.020", "sp": "library|Lac Courte Oreilles Tribal Code of Law|VEH|VEH.3|VEH.3.12|VEH.3.12.020", "c": [{"t": "(a)", "p": "/us/nsn/lco/council/code/VEH.3.12.020#(a)", "et": "para", "sc": "Section VEH.3.12.020(a)", "x": "Lends to another a registration plate for display upon a vehicle for which "}, {"t": "(b)", "p": "/us/nsn/lco/council/code/VEH.3.12.020#(b)", "et": "para", "sc": "Section VEH.3.12.020(b)", "x": "Displays upon a vehicle a registration plate not issued for such vehicle or"}, {"t": "(c)", "p": "/us/nsn/lco/council/code/VEH.3.12.020#(c)", "et": "para", "sc": "Section VEH.3.12.020(c)", "x": "Willfully twists, paints, alters or adds to or cuts off any portion of a re"}]}, {"t": "VEH.3.12.030 Special Registration Plates", "p": "/us/nsn/lco/council/code/VEH.3.12.030", "et": "section", "sc": "Section VEH.3.12.030", "sp": "library|Lac Courte Oreilles Tribal Code of Law|VEH|VEH.3|VEH.3.12|VEH.3.12.030"}]}, {"t": "Subchapter VEH.3.13 When Registration Is to Be Suspended", "p": "/us/nsn/lco/council/code/VEH.3.13", "et": "container", "sc": "Subchapter VEH.3.13", "sp": "library|Lac Courte Oreilles Tribal Code of Law|VEH|VEH.3|VEH.3.13", "c": [{"t": "VEH.3.13.010 When Suspended", "p": "/us/nsn/lco/council/code/VEH.3.13.010", "et": "section", "sc": "Section VEH.3.13.010", "sp": "library|Lac Courte Oreilles Tribal Code of Law|VEH|VEH.3|VEH.3.13|VEH.3.13.010", "c": [{"t": "(a)", "p": "/us/nsn/lco/council/code/VEH.3.13.010#(a)", "et": "para", "sc": "Section VEH.3.13.010(a)", "c": [{"t": "(1)", "p": "/us/nsn/lco/council/code/VEH.3.13.010#(a)(1)", "et": "para", "sc": "Section VEH.3.13.010(a)(1)", "x": "The registration was completed through fraud or error and the person who re"}, {"t": "(2)", "p": "/us/nsn/lco/council/code/VEH.3.13.010#(a)(2)", "et": "para", "sc": "Section VEH.3.13.010(a)(2)", "x": "The required fee has not been paid and the same is not paid upon reasonable"}, {"t": "(3)", "p": "/us/nsn/lco/council/code/VEH.3.13.010#(a)(3)", "et": "para", "sc": "Section VEH.3.13.010(a)(3)", "x": "Suspension of registration is specified by an authority under Section VEH.3"}, {"t": "(4)", "p": "/us/nsn/lco/council/code/VEH.3.13.010#(a)(4)", "et": "para", "sc": "Section VEH.3.13.010(a)(4)", "x": "The applicant fails, upon reasonable notice and demand, to furnish proof of"}, {"t": "(5)", "p": "/us/nsn/lco/council/code/VEH.3.13.010#(a)(5)", "et": "para", "sc": "Section VEH.3.13.010(a)(5)", "x": "The licensee of a vehicle registered under Section VEH.3.7.010 has not been"}], "x": "The department shall suspend the registration of a vehicle when:"}, {"t": "(b)", "p": "/us/nsn/lco/council/code/VEH.3.13.010#(b)", "et": "para", "sc": "Section VEH.3.13.010(b)", "x": "Any registration suspended pursuant to this section continues to be suspend"}, {"t": "(c)", "p": "/us/nsn/lco/council/code/VEH.3.13.010#(c)", "et": "para", "sc": "Section VEH.3.13.010(c)", "x": "Whenever the registration of a vehicle is suspended under this section, the"}]}, {"t": "VEH.3.13.020 Transfer of Vehicle Ownership While Registration Suspended", "p": "/us/nsn/lco/council/code/VEH.3.13.020", "et": "section", "sc": "Section VEH.3.13.020", "sp": "library|Lac Courte Oreilles Tribal Code of Law|VEH|VEH.3|VEH.3.13|VEH.3.13.020", "c": [{"t": "(a)", "p": "/us/nsn/lco/council/code/VEH.3.13.020#(a)", "et": "para", "sc": "Section VEH.3.13.020(a)", "x": "No owner may transfer the ownership or registration of any vehicle whose re"}, {"t": "(b)", "p": "/us/nsn/lco/council/code/VEH.3.13.020#(b)", "et": "para", "sc": "Section VEH.3.13.020(b)", "x": "Any person violating this section may be subject to a fine of not more than"}, {"t": "(c)", "p": "/us/nsn/lco/council/code/VEH.3.13.020#(c)", "et": "para", "sc": "Section VEH.3.13.020(c)", "x": "This section does not apply to or affect the registration of any vehicle so"}]}]}, {"t": "Subchapter VEH.3.14 Nonmoving Violations", "p": "/us/nsn/lco/council/code/VEH.3.14", "et": "container", "sc": "Subchapter VEH.3.14", "sp": "library|Lac Courte Oreilles Tribal Code of Law|VEH|VEH.3|VEH.3.14", "c": [{"t": "VEH.3.14.010 Non-Moving Violation", "p": "/us/nsn/lco/council/code/VEH.3.14.010", "et": "section", "sc": "Section VEH.3.14.010", "sp": "library|Lac Courte Oreilles Tribal Code of Law|VEH|VEH.3|VEH.3.14|VEH.3.14.010", "c": [{"t": "(a)", "p": "/us/nsn/lco/council/code/VEH.3.14.010#(a)", "et": "para", "sc": "Section VEH.3.14.010(a)", "c": [{"t": "(1)", "p": "/us/nsn/lco/council/code/VEH.3.14.010#(a)(1)", "et": "para", "sc": "Section VEH.3.14.010(a)(1)", "x": "\"Authority\" means a Tribal Authority, a local authority, or a state agency."}, {"t": "(2)", "p": "/us/nsn/lco/council/code/VEH.3.14.010#(a)(2)", "et": "para", "sc": "Section VEH.3.14.010(a)(2)", "x": "\"Forfeiture\" includes a fine established under this ordinance."}, {"t": "(3)", "p": "/us/nsn/lco/council/code/VEH.3.14.010#(a)(3)", "et": "para", "sc": "Section VEH.3.14.010(a)(3)", "x": "\"Nonmoving traffic violation\" is any parking of a vehicle in violation of a"}], "x": "As used in this section:"}, {"t": "(b)", "p": "/us/nsn/lco/council/code/VEH.3.14.010#(b)", "et": "para", "sc": "Section VEH.3.14.010(b)", "x": "If the person does not pay the forfeiture or appear in court in response to"}, {"t": "(c)", "p": "/us/nsn/lco/council/code/VEH.3.14.010#(c)", "et": "para", "sc": "Section VEH.3.14.010(c)", "x": "If the person does not pay the forfeiture or appear in court in response to"}]}, {"t": "VEH.3.14.020 Penalty for Operating Unregistered or Improperly Registered Vehicle", "p": "/us/nsn/lco/council/code/VEH.3.14.020", "et": "section", "sc": "Section VEH.3.14.020", "sp": "library|Lac Courte Oreilles Tribal Code of Law|VEH|VEH.3|VEH.3.14|VEH.3.14.020", "c": [{"t": "(a)", "p": "/us/nsn/lco/council/code/VEH.3.14.020#(a)", "et": "para", "sc": "Section VEH.3.14.020(a)", "c": [{"t": "(1)", "p": "/us/nsn/lco/council/code/VEH.3.14.020#(a)(1)", "et": "para", "sc": "Section VEH.3.14.020(a)(1)", "x": "A vehicle may be operated by a private person after the date of purchase of"}], "x": "It is unlawful for any person to operate or for an owner to consent to bein"}, {"t": "(b)", "p": "/us/nsn/lco/council/code/VEH.3.14.020#(b)", "et": "para", "sc": "Section VEH.3.14.020(b)", "x": "All vehicles subject to renewal or registration may be operated provided th"}, {"t": "(c)", "p": "/us/nsn/lco/council/code/VEH.3.14.020#(c)", "et": "para", "sc": "Section VEH.3.14.020(c)", "c": [{"t": "(1)", "p": "/us/nsn/lco/council/code/VEH.3.14.020#(c)(1)", "et": "para", "sc": "Section VEH.3.14.020(c)(1)", "x": "Any person who violates par. (a) or (b), where the vehicle used is an autom"}], "x": "Unless application for re-registration has been made as required by Section"}, {"t": "(d)", "p": "/us/nsn/lco/council/code/VEH.3.14.020#(d)", "et": "para", "sc": "Section VEH.3.14.020(d)", "x": "Any person who violates par. (a) or (b), where the vehicle used is vehicle "}]}]}]}, {"t": "Chapter VEH.4 All-Terrain Vehicles and Utility Task Vehicles", "p": "/us/nsn/lco/council/code/VEH.4", "et": "container", "sc": "Chapter VEH.4", "sp": "library|Lac Courte Oreilles Tribal Code of Law|VEH|VEH.4", "c": [{"t": "Subchapter VEH.4.1 Introduction", "p": "/us/nsn/lco/council/code/VEH.4.1", "et": "container", "sc": "Subchapter VEH.4.1", "sp": "library|Lac Courte Oreilles Tribal Code of Law|VEH|VEH.4|VEH.4.1", "c": [{"t": "VEH.4.1.010 Title", "p": "/us/nsn/lco/council/code/VEH.4.1.010", "et": "section", "sc": "Section VEH.4.1.010", "sp": "library|Lac Courte Oreilles Tribal Code of Law|VEH|VEH.4|VEH.4.1|VEH.4.1.010"}, {"t": "VEH.4.1.020 Authority", "p": "/us/nsn/lco/council/code/VEH.4.1.020", "et": "section", "sc": "Section VEH.4.1.020", "sp": "library|Lac Courte Oreilles Tribal Code of Law|VEH|VEH.4|VEH.4.1|VEH.4.1.020"}, {"t": "VEH.4.1.030 Purpose", "p": "/us/nsn/lco/council/code/VEH.4.1.030", "et": "section", "sc": "Section VEH.4.1.030", "sp": "library|Lac Courte Oreilles Tribal Code of Law|VEH|VEH.4|VEH.4.1|VEH.4.1.030"}, {"t": "VEH.4.1.040 Scope", "p": "/us/nsn/lco/council/code/VEH.4.1.040", "et": "section", "sc": "Section VEH.4.1.040", "sp": "library|Lac Courte Oreilles Tribal Code of Law|VEH|VEH.4|VEH.4.1|VEH.4.1.040"}, {"t": "VEH.4.1.050 Effective Date", "p": "/us/nsn/lco/council/code/VEH.4.1.050", "et": "section", "sc": "Section VEH.4.1.050", "sp": "library|Lac Courte Oreilles Tribal Code of Law|VEH|VEH.4|VEH.4.1|VEH.4.1.050"}, {"t": "VEH.4.1.060 Severability and Non-Liability", "p": "/us/nsn/lco/council/code/VEH.4.1.060", "et": "section", "sc": "Section VEH.4.1.060", "sp": "library|Lac Courte Oreilles Tribal Code of Law|VEH|VEH.4|VEH.4.1|VEH.4.1.060"}, {"t": "VEH.4.1.070 Non-Exclusive Remedy", "p": "/us/nsn/lco/council/code/VEH.4.1.070", "et": "section", "sc": "Section VEH.4.1.070", "sp": "library|Lac Courte Oreilles Tribal Code of Law|VEH|VEH.4|VEH.4.1|VEH.4.1.070"}, {"t": "VEH.4.1.080 Interpretation", "p": "/us/nsn/lco/council/code/VEH.4.1.080", "et": "section", "sc": "Section VEH.4.1.080", "sp": "library|Lac Courte Oreilles Tribal Code of Law|VEH|VEH.4|VEH.4.1|VEH.4.1.080", "c": [{"t": "(a)", "p": "/us/nsn/lco/council/code/VEH.4.1.080#(a)", "et": "para", "sc": "Section VEH.4.1.080(a)", "x": "Shall be liberally construed in favor of the Tribe;"}, {"t": "(b)", "p": "/us/nsn/lco/council/code/VEH.4.1.080#(b)", "et": "para", "sc": "Section VEH.4.1.080(b)", "x": "Shall not be deemed a limitation or repeal of any other tribal power or aut"}]}]}, {"t": "Subchapter VEH.4.2 Definitions", "p": "/us/nsn/lco/council/code/VEH.4.2", "et": "container", "sc": "Subchapter VEH.4.2", "sp": "library|Lac Courte Oreilles Tribal Code of Law|VEH|VEH.4|VEH.4.2", "c": [{"t": "VEH.4.2.010 General Definitions", "p": "/us/nsn/lco/council/code/VEH.4.2.010", "et": "section", "sc": "Section VEH.4.2.010", "sp": "library|Lac Courte Oreilles Tribal Code of Law|VEH|VEH.4|VEH.4.2|VEH.4.2.010", "c": [{"t": "(a)", "p": "/us/nsn/lco/council/code/VEH.4.2.010#(a)", "et": "para", "sc": "Section VEH.4.2.010(a)", "x": "\"All-terrain vehicle\" and \"ATV\" means an engine-driven device which has a n"}, {"t": "(b)", "p": "/us/nsn/lco/council/code/VEH.4.2.010#(b)", "et": "para", "sc": "Section VEH.4.2.010(b)", "x": "\"County\" means Sawyer County, a political subdivision of Wisconsin."}, {"t": "(c)", "p": "/us/nsn/lco/council/code/VEH.4.2.010#(c)", "et": "para", "sc": "Section VEH.4.2.010(c)", "x": "\"County Road\" means any road that is maintained by the County that exists w"}, {"t": "(d)", "p": "/us/nsn/lco/council/code/VEH.4.2.010#(d)", "et": "para", "sc": "Section VEH.4.2.010(d)", "x": "\"Highway\" means all public ways and thoroughfares and bridges and the same."}, {"t": "(e)", "p": "/us/nsn/lco/council/code/VEH.4.2.010#(e)", "et": "para", "sc": "Section VEH.4.2.010(e)", "x": "\"Purpose of access from lodging\" means for the purpose of traveling for the"}, {"t": "(f)", "p": "/us/nsn/lco/council/code/VEH.4.2.010#(f)", "et": "para", "sc": "Section VEH.4.2.010(f)", "x": "\"Purpose of residential access\" means for the purpose of traveling for the "}, {"t": "(g)", "p": "/us/nsn/lco/council/code/VEH.4.2.010#(g)", "et": "para", "sc": "Section VEH.4.2.010(g)", "x": "\"Reservation\" means the Lac Courte Oreilles Reservation as established unde"}, {"t": "(h)", "p": "/us/nsn/lco/council/code/VEH.4.2.010#(h)", "et": "para", "sc": "Section VEH.4.2.010(h)", "x": "\"Reservation road\" means any road that is maintained by the tribal roads de"}, {"t": "(i)", "p": "/us/nsn/lco/council/code/VEH.4.2.010#(i)", "et": "para", "sc": "Section VEH.4.2.010(i)", "x": "\"Road, trail, or street\" means any path that may or may not be paved which "}, {"t": "(j)", "p": "/us/nsn/lco/council/code/VEH.4.2.010#(j)", "et": "para", "sc": "Section VEH.4.2.010(j)", "x": "\"Roadway\" means that portion of a highway between the regularly established"}, {"t": "(k)", "p": "/us/nsn/lco/council/code/VEH.4.2.010#(k)", "et": "para", "sc": "Section VEH.4.2.010(k)", "x": "\"Nonmember\" or \"Non-Tribal Member\" means a person is not currently enrolled"}, {"t": "(l)", "p": "/us/nsn/lco/council/code/VEH.4.2.010#(l)", "et": "para", "sc": "Section VEH.4.2.010(l)", "x": "\"Off-highway motorcycle\" means a two-wheeled motor vehicle that is straddle"}, {"t": "(m)", "p": "/us/nsn/lco/council/code/VEH.4.2.010#(m)", "et": "para", "sc": "Section VEH.4.2.010(m)", "x": "\"Tribal Governing Board\" means the Tribal Governing Board of the Lac Courte"}, {"t": "(n)", "p": "/us/nsn/lco/council/code/VEH.4.2.010#(n)", "et": "para", "sc": "Section VEH.4.2.010(n)", "x": "\"Tribal Member\" means an enrolled member of the Lac Courte Oreilles Band of"}, {"t": "(o)", "p": "/us/nsn/lco/council/code/VEH.4.2.010#(o)", "et": "para", "sc": "Section VEH.4.2.010(o)", "x": "\"Tribe\" means the Lac Courte Oreilles Band of Lake Superior Chippewa Indian"}, {"t": "(p)", "p": "/us/nsn/lco/council/code/VEH.4.2.010#(p)", "et": "para", "sc": "Section VEH.4.2.010(p)", "x": "\"Utility-task vehicle\" and \"UTV\" as a commercially designed and manufacture"}]}]}, {"t": "Subchapter VEH.4.3 Rules of Operation", "p": "/us/nsn/lco/council/code/VEH.4.3", "et": "container", "sc": "Subchapter VEH.4.3", "sp": "library|Lac Courte Oreilles Tribal Code of Law|VEH|VEH.4|VEH.4.3", "c": [{"t": "VEH.4.3.010 Authorized Operation", "p": "/us/nsn/lco/council/code/VEH.4.3.010", "et": "section", "sc": "Section VEH.4.3.010", "sp": "library|Lac Courte Oreilles Tribal Code of Law|VEH|VEH.4|VEH.4.3|VEH.4.3.010", "c": [{"t": "(a)", "p": "/us/nsn/lco/council/code/VEH.4.3.010#(a)", "et": "para", "sc": "Section VEH.4.3.010(a)", "x": "All ATV/UTV operators shall comply with posted speed limits, stop signs, tr"}, {"t": "(b)", "p": "/us/nsn/lco/council/code/VEH.4.3.010#(b)", "et": "para", "sc": "Section VEH.4.3.010(b)", "c": [{"t": "(1)", "p": "/us/nsn/lco/council/code/VEH.4.3.010#(b)(1)", "et": "para", "sc": "Section VEH.4.3.010(b)(1)", "x": "On all marked roads and marked trails within the boundaries of the Lac Cour"}, {"t": "(2)", "p": "/us/nsn/lco/council/code/VEH.4.3.010#(b)(2)", "et": "para", "sc": "Section VEH.4.3.010(b)(2)", "x": "On all state and county highways located within the boundaries of the Lac C"}, {"t": "(3)", "p": "/us/nsn/lco/council/code/VEH.4.3.010#(b)(3)", "et": "para", "sc": "Section VEH.4.3.010(b)(3)", "x": "On tribally-owned lands whose purpose is to hunt, fish or gather within the"}, {"t": "(4)", "p": "/us/nsn/lco/council/code/VEH.4.3.010#(b)(4)", "et": "para", "sc": "Section VEH.4.3.010(b)(4)", "x": "All persons under the age of 18 are required to wear a helmet and eye prote"}, {"t": "(5)", "p": "/us/nsn/lco/council/code/VEH.4.3.010#(b)(5)", "et": "para", "sc": "Section VEH.4.3.010(b)(5)", "x": "ATV operation is limited to one person per vehicle unless designed for a pa"}, {"t": "(6)", "p": "/us/nsn/lco/council/code/VEH.4.3.010#(b)(6)", "et": "para", "sc": "Section VEH.4.3.010(b)(6)", "x": "No passengers allowed for operators under the age 18."}, {"t": "(7)", "p": "/us/nsn/lco/council/code/VEH.4.3.010#(b)(7)", "et": "para", "sc": "Section VEH.4.3.010(b)(7)", "x": "Infants are prohibited from being passengers in an ATV/UTV during its opera"}], "x": "Operators may operate an ATV/UTV:"}]}, {"t": "VEH.4.3.020 Unauthorized Operations Operators may not operate an ATV/UTV:", "p": "/us/nsn/lco/council/code/VEH.4.3.020", "et": "section", "sc": "Section VEH.4.3.020", "sp": "library|Lac Courte Oreilles Tribal Code of Law|VEH|VEH.4|VEH.4.3|VEH.4.3.020", "c": [{"t": "(a)", "p": "/us/nsn/lco/council/code/VEH.4.3.020#(a)", "et": "para", "sc": "Section VEH.4.3.020(a)", "x": "In any reckless or negligent way so as to endanger the person or property o"}, {"t": "(b)", "p": "/us/nsn/lco/council/code/VEH.4.3.020#(b)", "et": "para", "sc": "Section VEH.4.3.020(b)", "x": "On the private property of another without the consent of the owner or less"}, {"t": "(c)", "p": "/us/nsn/lco/council/code/VEH.4.3.020#(c)", "et": "para", "sc": "Section VEH.4.3.020(c)", "x": "On allotted lands to tribal members within the exterior boundaries of the r"}, {"t": "(d)", "p": "/us/nsn/lco/council/code/VEH.4.3.020#(d)", "et": "para", "sc": "Section VEH.4.3.020(d)", "x": "When under the influence of alcohol, drugs or any other altering substance."}, {"t": "(e)", "p": "/us/nsn/lco/council/code/VEH.4.3.020#(e)", "et": "para", "sc": "Section VEH.4.3.020(e)", "x": "When within 150 feet of a dwelling at a speed exceeding ten (10) miles per "}, {"t": "(f)", "p": "/us/nsn/lco/council/code/VEH.4.3.020#(f)", "et": "para", "sc": "Section VEH.4.3.020(f)", "x": "On land owned in fee simple that belongs to a non-tribal member within the "}, {"t": "(g)", "p": "/us/nsn/lco/council/code/VEH.4.3.020#(g)", "et": "para", "sc": "Section VEH.4.3.020(g)", "x": "No operator may cause excessive, unusual noise, or noise pollution while op"}]}, {"t": "VEH.4.3.030 Operation on County Roads or Highways", "p": "/us/nsn/lco/council/code/VEH.4.3.030", "et": "section", "sc": "Section VEH.4.3.030", "sp": "library|Lac Courte Oreilles Tribal Code of Law|VEH|VEH.4|VEH.4.3|VEH.4.3.030", "c": [{"t": "(a)", "p": "/us/nsn/lco/council/code/VEH.4.3.030#(a)", "et": "para", "sc": "Section VEH.4.3.030(a)", "x": "Highways.  ATV/UTV all-terrain vehicle may operate on a state highway or co"}, {"t": "(b)", "p": "/us/nsn/lco/council/code/VEH.4.3.030#(b)", "et": "para", "sc": "Section VEH.4.3.030(b)", "x": "Operation on roadway or pavement.  all-terrain vehicles may operate on the "}, {"t": "(c)", "p": "/us/nsn/lco/council/code/VEH.4.3.030#(c)", "et": "para", "sc": "Section VEH.4.3.030(c)", "c": [{"t": "(1)", "p": "/us/nsn/lco/council/code/VEH.4.3.030#(c)(1)", "et": "para", "sc": "Section VEH.4.3.030(c)(1)", "x": "At a distance of ten (10) or more feet from the shoulder of the roadway alo"}, {"t": "(2)", "p": "/us/nsn/lco/council/code/VEH.4.3.030#(c)(2)", "et": "para", "sc": "Section VEH.4.3.030(c)(2)", "x": "During hours of darkness in the same direction as motor vehicle traffic in "}, {"t": "(3)", "p": "/us/nsn/lco/council/code/VEH.4.3.030#(c)(3)", "et": "para", "sc": "Section VEH.4.3.030(c)(3)", "x": "Not in excess of the speed limits of the adjacent roadway."}], "x": "Operation adjacent to roadway.  all-terrain vehicles may operate adjacent t"}]}, {"t": "VEH.4.3.040 Hours of Operation", "p": "/us/nsn/lco/council/code/VEH.4.3.040", "et": "section", "sc": "Section VEH.4.3.040", "sp": "library|Lac Courte Oreilles Tribal Code of Law|VEH|VEH.4|VEH.4.3|VEH.4.3.040", "c": [{"t": "(a)", "p": "/us/nsn/lco/council/code/VEH.4.3.040#(a)", "et": "para", "sc": "Section VEH.4.3.040(a)", "x": "Hours of Operation for recreational use of ATV/UTV on the Lac Courte Oreill"}, {"t": "(b)", "p": "/us/nsn/lco/council/code/VEH.4.3.040#(b)", "et": "para", "sc": "Section VEH.4.3.040(b)", "x": "Hours of Operation of ATV/UTV use for the exercise of treaty hunting, fishi"}]}, {"t": "VEH.4.3.050 Logging Areas and Sacred Sites", "p": "/us/nsn/lco/council/code/VEH.4.3.050", "et": "section", "sc": "Section VEH.4.3.050", "sp": "library|Lac Courte Oreilles Tribal Code of Law|VEH|VEH.4|VEH.4.3|VEH.4.3.050", "c": [{"t": "(a)", "p": "/us/nsn/lco/council/code/VEH.4.3.050#(a)", "et": "para", "sc": "Section VEH.4.3.050(a)", "x": "Areas located on the reservation that are marked as \"logging areas\" or area"}]}, {"t": "VEH.4.3.060 Trail Designation", "p": "/us/nsn/lco/council/code/VEH.4.3.060", "et": "section", "sc": "Section VEH.4.3.060", "sp": "library|Lac Courte Oreilles Tribal Code of Law|VEH|VEH.4|VEH.4.3|VEH.4.3.060", "c": [{"t": "(a)", "p": "/us/nsn/lco/council/code/VEH.4.3.060#(a)", "et": "para", "sc": "Section VEH.4.3.060(a)", "x": "All ATV/UTV trails shall be designated for use by the LCO Conservation Depa"}]}, {"t": "VEH.4.3.070 Northwoods Beach City Limits", "p": "/us/nsn/lco/council/code/VEH.4.3.070", "et": "section", "sc": "Section VEH.4.3.070", "sp": "library|Lac Courte Oreilles Tribal Code of Law|VEH|VEH.4|VEH.4.3|VEH.4.3.070"}]}, {"t": "Subchapter VEH.4.4 Enforcement", "p": "/us/nsn/lco/council/code/VEH.4.4", "et": "container", "sc": "Subchapter VEH.4.4", "sp": "library|Lac Courte Oreilles Tribal Code of Law|VEH|VEH.4|VEH.4.4", "c": [{"t": "VEH.4.4.010 Enforcement", "p": "/us/nsn/lco/council/code/VEH.4.4.010", "et": "section", "sc": "Section VEH.4.4.010", "sp": "library|Lac Courte Oreilles Tribal Code of Law|VEH|VEH.4|VEH.4.4|VEH.4.4.010"}, {"t": "VEH.4.4.020 Tribal Court", "p": "/us/nsn/lco/council/code/VEH.4.4.020", "et": "section", "sc": "Section VEH.4.4.020", "sp": "library|Lac Courte Oreilles Tribal Code of Law|VEH|VEH.4|VEH.4.4|VEH.4.4.020"}, {"t": "VEH.4.4.030 Tribal ATV/UTV Registration", "p": "/us/nsn/lco/council/code/VEH.4.4.030", "et": "section", "sc": "Section VEH.4.4.030", "sp": "library|Lac Courte Oreilles Tribal Code of Law|VEH|VEH.4|VEH.4.4|VEH.4.4.030", "c": [{"t": "(a)", "p": "/us/nsn/lco/council/code/VEH.4.4.030#(a)", "et": "para", "sc": "Section VEH.4.4.030(a)", "x": "All ATV/UTV that operate on the Reservation shall be registered  with the L"}, {"t": "(b)", "p": "/us/nsn/lco/council/code/VEH.4.4.030#(b)", "et": "para", "sc": "Section VEH.4.4.030(b)", "x": "Each ATV/UTV shall be issued a unique ATV/UTV permit that shall be prominen"}, {"t": "(c)", "p": "/us/nsn/lco/council/code/VEH.4.4.030#(c)", "et": "para", "sc": "Section VEH.4.4.030(c)", "x": "The registration of the ATV/UTV shall be renewed every two years."}, {"t": "(d)", "p": "/us/nsn/lco/council/code/VEH.4.4.030#(d)", "et": "para", "sc": "Section VEH.4.4.030(d)", "x": "The registration fee shall not exceed $50.00 per ATV/UTV."}, {"t": "(e)", "p": "/us/nsn/lco/council/code/VEH.4.4.030#(e)", "et": "para", "sc": "Section VEH.4.4.030(e)", "x": "Failure to register ones ATV/UTV may result in immediate impoundment of the"}]}]}, {"t": "Subchapter VEH.4.5 Penalties", "p": "/us/nsn/lco/council/code/VEH.4.5", "et": "container", "sc": "Subchapter VEH.4.5", "sp": "library|Lac Courte Oreilles Tribal Code of Law|VEH|VEH.4|VEH.4.5", "c": [{"t": "VEH.4.5.010 Penalties", "p": "/us/nsn/lco/council/code/VEH.4.5.010", "et": "section", "sc": "Section VEH.4.5.010", "sp": "library|Lac Courte Oreilles Tribal Code of Law|VEH|VEH.4|VEH.4.5|VEH.4.5.010", "c": [{"t": "(a)", "p": "/us/nsn/lco/council/code/VEH.4.5.010#(a)", "et": "para", "sc": "Section VEH.4.5.010(a)", "x": "Any person who violates any section of this code shall pay a forfeiture of "}, {"t": "(b)", "p": "/us/nsn/lco/council/code/VEH.4.5.010#(b)", "et": "para", "sc": "Section VEH.4.5.010(b)", "x": "For any ATV/UTV that is operating outside the posted roadways or ATV/UTV tr"}, {"t": "(c)", "p": "/us/nsn/lco/council/code/VEH.4.5.010#(c)", "et": "para", "sc": "Section VEH.4.5.010(c)", "x": "For any ATV/UTV that does not have tribal registration or tribal plates dis"}, {"t": "(d)", "p": "/us/nsn/lco/council/code/VEH.4.5.010#(d)", "et": "para", "sc": "Section VEH.4.5.010(d)", "x": "Any ATV/UTV that is confiscated by Tribal Law enforcement may be released a"}, {"t": "(e)", "p": "/us/nsn/lco/council/code/VEH.4.5.010#(e)", "et": "para", "sc": "Section VEH.4.5.010(e)", "x": "Any ATV/UTV that is impounded by Tribal Law Enforcement may be released to "}]}, {"t": "VEH.4.5.020 Citations", "p": "/us/nsn/lco/council/code/VEH.4.5.020", "et": "section", "sc": "Section VEH.4.5.020", "sp": "library|Lac Courte Oreilles Tribal Code of Law|VEH|VEH.4|VEH.4.5|VEH.4.5.020", "c": [{"t": "(a)", "p": "/us/nsn/lco/council/code/VEH.4.5.020#(a)", "et": "para", "sc": "Section VEH.4.5.020(a)", "x": "Operation of an ATV/UTV without fully operational vehicle lights, pursuant "}, {"t": "(b)", "p": "/us/nsn/lco/council/code/VEH.4.5.020#(b)", "et": "para", "sc": "Section VEH.4.5.020(b)", "x": "Operation of an ATV/UTV in excess of posted speed limits, pursuant to \u00a7 VEH"}, {"t": "(c)", "p": "/us/nsn/lco/council/code/VEH.4.5.020#(c)", "et": "para", "sc": "Section VEH.4.5.020(c)", "x": "Operation of an ATV/UTV outside of the posted roadways or marked paths/trai"}, {"t": "(d)", "p": "/us/nsn/lco/council/code/VEH.4.5.020#(d)", "et": "para", "sc": "Section VEH.4.5.020(d)", "x": "Operation of an ATV/UTV without protective safety equipment, pursuant to \u00a7 "}, {"t": "(e)", "p": "/us/nsn/lco/council/code/VEH.4.5.020#(e)", "et": "para", "sc": "Section VEH.4.5.020(e)", "x": "Operation of an ATV/UTV near sacred sites or on private property, pursuant "}, {"t": "(f)", "p": "/us/nsn/lco/council/code/VEH.4.5.020#(f)", "et": "para", "sc": "Section VEH.4.5.020(f)", "x": "Operation of an ATV/UTV in a reckless or negligent manner, pursuant to \u00a7 VE"}, {"t": "(g)", "p": "/us/nsn/lco/council/code/VEH.4.5.020#(g)", "et": "para", "sc": "Section VEH.4.5.020(g)", "x": "Operation of an ATV/UTV with an unauthorized passenger, pursuant to \u00a7 VEH.4"}, {"t": "(h)", "p": "/us/nsn/lco/council/code/VEH.4.5.020#(h)", "et": "para", "sc": "Section VEH.4.5.020(h)", "x": "Operation of an ATV/UTV after hours of operations, pursuant to \u00a7 VEH.4.3.04"}, {"t": "(i)", "p": "/us/nsn/lco/council/code/VEH.4.5.020#(i)", "et": "para", "sc": "Section VEH.4.5.020(i)", "x": "Operation of an ATV/UTV without current registration, pursuant to \u00a7 VEH.4.4"}, {"t": "(j)", "p": "/us/nsn/lco/council/code/VEH.4.5.020#(j)", "et": "para", "sc": "Section VEH.4.5.020(j)", "x": "Operation of an ATV/UTV when under the influence of alcohol, drugs, or any "}, {"t": "(k)", "p": "/us/nsn/lco/council/code/VEH.4.5.020#(k)", "et": "para", "sc": "Section VEH.4.5.020(k)", "x": "Operation of an ATV/UTV without a muffler pursuant to \u00a7VEH.4.2.010(a) and ("}, {"t": "(l)", "p": "/us/nsn/lco/council/code/VEH.4.5.020#(l)", "et": "para", "sc": "Section VEH.4.5.020(l)", "x": "Operation of an ATV/UTV causing excessive noise, unusual noise, and or nois"}]}, {"t": "VEH.4.5.030 Citation Procedure", "p": "/us/nsn/lco/council/code/VEH.4.5.030", "et": "section", "sc": "Section VEH.4.5.030", "sp": "library|Lac Courte Oreilles Tribal Code of Law|VEH|VEH.4|VEH.4.5|VEH.4.5.030", "c": [{"t": "(a)", "p": "/us/nsn/lco/council/code/VEH.4.5.030#(a)", "et": "para", "sc": "Section VEH.4.5.030(a)", "x": "All citations issued under this code shall be prosecuted under the Lac Cour"}]}, {"t": "VEH.4.5.040 Confiscated or Impoundment Procedure", "p": "/us/nsn/lco/council/code/VEH.4.5.040", "et": "section", "sc": "Section VEH.4.5.040", "sp": "library|Lac Courte Oreilles Tribal Code of Law|VEH|VEH.4|VEH.4.5|VEH.4.5.040", "c": [{"t": "(a)", "p": "/us/nsn/lco/council/code/VEH.4.5.040#(a)", "et": "para", "sc": "Section VEH.4.5.040(a)", "x": "Any ATV/UTV that is confiscated by Tribal Law Enforcement may be released a"}, {"t": "(b)", "p": "/us/nsn/lco/council/code/VEH.4.5.040#(b)", "et": "para", "sc": "Section VEH.4.5.040(b)", "x": "Any ATV/UTV that is impounded by Tribal Law Enforcement may be released to "}]}]}]}]}